dist_gb/test.py
dist_gb/src/Binomialdistribution.py
dist_gb/src/Gaussiandistribution.py
dist_gb/src/Generaldistribution.py
dist_gb/src/__init__.py
dist_gb_akhlaqi-0.0.4.dist-info/METADATA
dist_gb_akhlaqi-0.0.4.dist-info/WHEEL
dist_gb_akhlaqi-0.0.4.dist-info/top_level.txt
dist_gb_akhlaqi-0.0.4.dist-info/RECORD
