Metadata-Version: 2.1
Name: dist-gb-akhlaqi
Version: 0.0.4
Summary: Gaussian and Binomial distributions
Author-email: Mohammad Yahya Akhlaqi <yahya.akhlaghi@gmail.com>
Project-URL: Homepage, https://github.com/myakhlaqi/distributions_package
Project-URL: Bug Tracker, https://github.com/myakhlaqi/distributions_package/issues
Classifier: Programming Language :: Python :: 3
Classifier: License :: OSI Approved :: MIT License
Classifier: Operating System :: OS Independent
Requires-Python: >=3.7
